flaskpress_themes/__init__.py
flaskpress_themes-0.1.5.dist-info/DESCRIPTION.rst
flaskpress_themes-0.1.5.dist-info/METADATA
flaskpress_themes-0.1.5.dist-info/RECORD
flaskpress_themes-0.1.5.dist-info/WHEEL
flaskpress_themes-0.1.5.dist-info/metadata.json
flaskpress_themes-0.1.5.dist-info/top_level.txt
